nif_dumper/__init__.py
nif_dumper/dumper.py
nif_dumper-1.0.3.dist-info/LICENSE
nif_dumper-1.0.3.dist-info/METADATA
nif_dumper-1.0.3.dist-info/WHEEL
nif_dumper-1.0.3.dist-info/entry_points.txt
nif_dumper-1.0.3.dist-info/top_level.txt
nif_dumper-1.0.3.dist-info/RECORD
