Metadata-Version: 2.1
Name: nif-dumper
Version: 1.0.3
Summary: A simple Python CLI tool to search and download NIF (Naruto Italian Forum) releases
Home-page: https://github.com/LightDestory/NIF-Dumper
Author: LightDestory
Author-email: apb231@gmail.com
Project-URL: Bug Tracker, https://github.com/LightDestory/NIF-Dumper/issues
Classifier: Development Status :: 5 - Production/Stable
Classifier: Environment :: Console
Classifier: License :: OSI Approved :: GNU General Public License v3 (GPLv3)
Classifier: Operating System :: OS Independent
Classifier: Programming Language :: Python :: 3
Classifier: Programming Language :: Python :: 3.7
Classifier: Programming Language :: Python :: 3.8
Classifier: Programming Language :: Python :: 3.9
Classifier: Programming Language :: Python :: 3.10
Classifier: Typing :: Typed
Requires-Python: >=3.7
License-File: LICENSE
Requires-Dist: requests (~=2.28.2)
Requires-Dist: inquirerpy (~=0.3.4)
Requires-Dist: beautifulsoup4 (~=4.12.2)
Requires-Dist: colorama (~=0.4.6)
Requires-Dist: termcolor (~=2.2.0)
